README.md
setup.py
decompose/__init__.py
decompose_mrobison.egg-info/PKG-INFO
decompose_mrobison.egg-info/SOURCES.txt
decompose_mrobison.egg-info/dependency_links.txt
decompose_mrobison.egg-info/top_level.txt