Metadata-Version: 2.1
Name: decompose-mrobison
Version: 0.0.2
Summary: A module for decomposing strings in the latin alphabet to the ascii subset.
Home-page: https://github.com/wts-dev/decompose
Author: Mike Robison
Author-email: mrobison@wts.edu
License: UNKNOWN
Platform: UNKNOWN
Classifier: Programming Language :: Python :: 3
Classifier: License :: OSI Approved :: MIT License
Classifier: Operating System :: OS Independent
